setup.py
reconstruct/__init__.py
reconstruct/adapters.py
reconstruct/core.py
reconstruct/debug.py
reconstruct/macros.py
reconstruct.egg-info/PKG-INFO
reconstruct.egg-info/SOURCES.txt
reconstruct.egg-info/dependency_links.txt
reconstruct.egg-info/not-zip-safe
reconstruct.egg-info/top_level.txt
reconstruct/formats/__init__.py
reconstruct/formats/archive/__init__.py
reconstruct/formats/archive/pkzip.py
reconstruct/formats/archive/rar.py
reconstruct/formats/audio/__init__.py
reconstruct/formats/audio/mp3.py
reconstruct/formats/audio/ogg.py
reconstruct/formats/audio/wav.py
reconstruct/formats/data/__init__.py
reconstruct/formats/data/cap.py
reconstruct/formats/document/__init__.py
reconstruct/formats/document/doc.py
reconstruct/formats/document/pdf.py
reconstruct/formats/document/postscript.py
reconstruct/formats/executable/__init__.py
reconstruct/formats/executable/elf32.py
reconstruct/formats/executable/pe32.py
reconstruct/formats/filesystem/__init__.py
reconstruct/formats/filesystem/cdfs.py
reconstruct/formats/filesystem/ext2.py
reconstruct/formats/filesystem/ext3.py
reconstruct/formats/filesystem/fat12.py
reconstruct/formats/filesystem/fat16.py
reconstruct/formats/filesystem/fat32.py
reconstruct/formats/filesystem/mbr.py
reconstruct/formats/filesystem/ntfs5.py
reconstruct/formats/graphics/__init__.py
reconstruct/formats/graphics/bmp.py
reconstruct/formats/graphics/emf.py
reconstruct/formats/graphics/gif.py
reconstruct/formats/graphics/jpeg.py
reconstruct/formats/graphics/png.py
reconstruct/formats/graphics/wmf.py
reconstruct/formats/video/__init__.py
reconstruct/formats/video/avi.py
reconstruct/formats/video/divx.py
reconstruct/formats/video/mpeg2.py
reconstruct/formats/video/mpeg3.py
reconstruct/lib/__init__.py
reconstruct/lib/binary.py
reconstruct/lib/bitstream.py
reconstruct/lib/container.py
reconstruct/lib/formatter.py
reconstruct/lib/hex.py
reconstruct/lib/path.py
reconstruct/lib/utils.py
reconstruct/protocols/__init__.py
reconstruct/protocols/ipstack.py
reconstruct/protocols/ss7stack.py
reconstruct/protocols/application/__init__.py
reconstruct/protocols/application/dns.py
reconstruct/protocols/application/ftp.py
