Metadata-Version: 1.0
Name: reconstruct
Version: 2.03
Summary: library for constructing (parsing and building) of binary and textual data structures
Home-page: http://construct.wikispaces.com/
Author: Symbols
Author-email: simplesymbols at gmail dot com
License: Public Domain
Keywords: parsing,binary,bitwise,bit level,constructing,struct
Platform: any
Classifier: Development Status :: 5 - Production/Stable
Classifier: Intended Audience :: Developers
Classifier: Intended Audience :: End Users/Desktop
Classifier: License :: Public Domain
Classifier: Operating System :: OS Independent
Classifier: Programming Language :: Python
Classifier: Topic :: Internet
Classifier: Topic :: Scientific/Engineering :: Information Analysis
Classifier: Topic :: Scientific/Engineering :: Interface Engine/Protocol Translator
Classifier: Topic :: Software Development :: Libraries :: Python Modules
Classifier: Topic :: System :: Networking
Classifier: Topic :: System :: Networking :: Monitoring
Classifier: Topic :: Text Processing
